teehistorian_py-2025.1.2.dist-info/METADATA
teehistorian_py-2025.1.2.dist-info/WHEEL
teehistorian_py-2025.1.2.dist-info/licenses/LICENSE
teehistorian_py/__init__.py
teehistorian_py/_rust.abi3.so
teehistorian_py/_rust.pyi
teehistorian_py/exceptions.py
teehistorian_py/py.typed
teehistorian_py/teehistorian_py.pyi
teehistorian_py/utils.py
teehistorian_py-2025.1.2.dist-info/RECORD
