Metadata-Version: 2.4
Name: teehistorian-py
Version: 2025.1.2
Classifier: Development Status :: 4 - Beta
Classifier: Intended Audience :: Developers
Classifier: License :: OSI Approved :: GNU Affero General Public License v3 or later (AGPLv3+)
Classifier: Programming Language :: Python :: 3
Classifier: Programming Language :: Python :: 3.8
Classifier: Programming Language :: Python :: 3.9
Classifier: Programming Language :: Python :: 3.10
Classifier: Programming Language :: Python :: 3.11
Classifier: Programming Language :: Python :: 3.12
Classifier: Programming Language :: Rust
Classifier: Programming Language :: Python :: Implementation :: CPython
Classifier: Topic :: Games/Entertainment
Classifier: Topic :: Software Development :: Libraries :: Python Modules
Classifier: Typing :: Typed
Requires-Dist: maturin>=1.0 ; extra == 'dev'
Requires-Dist: pytest>=7.0 ; extra == 'dev'
Requires-Dist: pytest-cov>=4.0 ; extra == 'dev'
Requires-Dist: black>=22.0 ; extra == 'dev'
Requires-Dist: isort>=5.0 ; extra == 'dev'
Requires-Dist: mypy>=1.0 ; extra == 'dev'
Requires-Dist: pre-commit>=2.0 ; extra == 'dev'
Requires-Dist: mkdocs>=1.5 ; extra == 'docs'
Requires-Dist: mkdocs-material>=9.0 ; extra == 'docs'
Requires-Dist: mkdocstrings[python]>=0.24 ; extra == 'docs'
Requires-Dist: pytest>=7.0 ; extra == 'test'
Requires-Dist: pytest-cov>=4.0 ; extra == 'test'
Requires-Dist: pytest-benchmark>=4.0 ; extra == 'test'
Provides-Extra: dev
Provides-Extra: docs
Provides-Extra: test
License-File: LICENSE
Summary: Python bindings for teehistorian with event processing
Keywords: teeworlds,ddnet,parser,gaming
Author-email: Avolicious <avolicious@kog.tw>
Maintainer-email: Avolicious <avolicious@kog.tw>
Requires-Python: >=3.8
Project-URL: Homepage, https://github.com/KoG-teeworlds/teehistorian-py
Project-URL: Documentation, https://teehistorian-py.readthedocs.io/
Project-URL: Repository, https://github.com/KoG-teeworlds/teehistorian-py
Project-URL: Bug Tracker, https://github.com/KoG-teeworlds/teehistorian-py/issues
Project-URL: Changelog, https://github.com/KoG-teeworlds/teehistorian-py/blob/main/CHANGELOG.md
